[ {
  "id" : "66f8dd3d-2b3a-4962-8be6-2fa557e11293",
  "name" : "Running",
  "type" : "CARDIO",
  "explanation" : "Run for 30 minutes",
  "medias" : [ {
    "url" : "http://example.com/video-cardio",
    "type" : "VIDEO"
  } ],
  "difficulty" : "INTERMEDIATE",
  "duration" : 30,
  "distance" : 5000,
  "custom" : true
}, {
  "id" : "5fec4526-bb6e-4f8b-895d-74d7068df232",
  "name" : "Push-ups",
  "type" : "STRENGTH",
  "explanation" : "Do 20 push-ups",
  "medias" : [ {
    "url" : "http://example.com/video-cardio",
    "type" : "VIDEO"
  } ],
  "difficulty" : "BEGINNER",
  "repetitions" : 20,
  "series" : 3,
  "custom" : false
}, {
  "id" : "749c0e77-1740-41c2-bc33-0cadca249dea",
  "name" : "Running",
  "type" : "CARDIO",
  "explanation" : "Run for 30 minutes",
  "medias" : [ {
    "url" : "http://example.com/video-cardio",
    "type" : "VIDEO"
  } ],
  "difficulty" : "INTERMEDIATE",
  "duration" : 30,
  "distance" : 5000,
  "custom" : false
}, {
  "id" : "c7284651-7982-4a47-a2e6-fd1b6ad760d2",
  "name" : "Push-ups",
  "type" : "STRENGTH",
  "explanation" : "Do 20 push-ups",
  "medias" : [ {
    "url" : "http://example.com/video-cardio",
    "type" : "VIDEO"
  } ],
  "difficulty" : "BEGINNER",
  "repetitions" : 20,
  "series" : 3,
  "custom" : false
} ]